cashappchecker.py
cashappchecker-0.0.1.dist-info/LICENSE
cashappchecker-0.0.1.dist-info/METADATA
cashappchecker-0.0.1.dist-info/WHEEL
cashappchecker-0.0.1.dist-info/top_level.txt
cashappchecker-0.0.1.dist-info/RECORD
