Metadata-Version: 2.1
Name: cashappchecker
Version: 0.0.1
Summary: A package that aims to help people handle CashApp web receipts
Author-email: Masen ANON <crnnn@duck.com>
Project-URL: Homepage, https://gitlab.com/crnnn/cashappchecker
Project-URL: Issues, https://gitlab.com/crnnn/cashappchecker/-/issues
Classifier: Programming Language :: Python :: 3
Classifier: License :: OSI Approved :: MIT License
Classifier: Operating System :: OS Independent
Requires-Python: >=3.11
License-File: LICENSE
